setup.cfg
setup.py
PubSub_Python.egg-info/PKG-INFO
PubSub_Python.egg-info/SOURCES.txt
PubSub_Python.egg-info/dependency_links.txt
PubSub_Python.egg-info/requires.txt
PubSub_Python.egg-info/top_level.txt
pubsub/__init__.py
pubsub/client.py
pubsub/tests/__init__.py
pubsub/tests/test_client.py