Metadata-Version: 1.1
Name: PubSub-Python
Version: 0.0.1
Summary: Simple Python client for interacting with Google Cloud Pub/Sub.
Home-page: https://github.com/tylertreat/PubSub-Python
Author: Tyler Treat
Author-email: ttreat31@gmail.com
License: Apache
Platform: UNKNOWN
Classifier: Development Status :: 4 - Beta
Classifier: Environment :: Web Environment
Classifier: Intended Audience :: Developers
Classifier: Operating System :: OS Independent
Classifier: Programming Language :: Python
